jsdaily/__main__.py
jsdaily/daily_archive.py
jsdaily/daily_config.py
jsdaily/daily_dependency.py
jsdaily/daily_logging.py
jsdaily/daily_postinstall.py
jsdaily/daily_reinstall.py
jsdaily/daily_uninstall.py
jsdaily/daily_update.py
jsdaily/daily_utility.py
jsdaily/libdependency/__init__.py
jsdaily/libdependency/aftermath.sh
jsdaily/libdependency/dependency_brew.sh
jsdaily/libdependency/dependency_pip.sh
jsdaily/libdependency/logging_brew.sh
jsdaily/libdependency/logging_pip.sh
jsdaily/libdependency/relink_pip.sh
jsdaily/liblogging/__init__.py
jsdaily/liblogging/logging_apm.sh
jsdaily/liblogging/logging_appstore.sh
jsdaily/liblogging/logging_brew.sh
jsdaily/liblogging/logging_cask.sh
jsdaily/liblogging/logging_dotapp.sh
jsdaily/liblogging/logging_gem.sh
jsdaily/liblogging/logging_macapp.sh
jsdaily/liblogging/logging_npm.sh
jsdaily/liblogging/logging_pip.sh
jsdaily/liblogging/relink_pip.sh
jsdaily/libprinstall/__init__.py
jsdaily/libprinstall/aftermath.sh
jsdaily/libprinstall/cleanup.sh
jsdaily/libprinstall/logging_brew.sh
jsdaily/libprinstall/logging_cask.sh
jsdaily/libprinstall/postinstall.sh
jsdaily/libprinstall/reinstall_brew.sh
jsdaily/libprinstall/reinstall_cask.sh
jsdaily/libuninstall/__init__.py
jsdaily/libuninstall/aftermath.sh
jsdaily/libuninstall/logging_brew.sh
jsdaily/libuninstall/logging_cask.sh
jsdaily/libuninstall/logging_pip.sh
jsdaily/libuninstall/relink_pip.sh
jsdaily/libuninstall/uninstall_brew.sh
jsdaily/libuninstall/uninstall_cask.sh
jsdaily/libuninstall/uninstall_pip.sh
jsdaily/libupdate/__init__.py
jsdaily/libupdate/aftermath.sh
jsdaily/libupdate/cleanup.sh
jsdaily/libupdate/logging_apm.sh
jsdaily/libupdate/logging_appstore.sh
jsdaily/libupdate/logging_brew.sh
jsdaily/libupdate/logging_cask.sh
jsdaily/libupdate/logging_gem.sh
jsdaily/libupdate/logging_npm.sh
jsdaily/libupdate/logging_pip.sh
jsdaily/libupdate/relink_pip.sh
jsdaily/libupdate/renew_brew.sh
jsdaily/libupdate/update_apm.sh
jsdaily-1.4.0.dist-info/LICENSE.txt
jsdaily-1.4.0.dist-info/METADATA
jsdaily-1.4.0.dist-info/RECORD
jsdaily-1.4.0.dist-info/WHEEL
jsdaily-1.4.0.dist-info/entry_points.txt
jsdaily-1.4.0.dist-info/top_level.txt
