Metadata-Version: 2.1
Name: jsdaily
Version: 1.4.0
Summary: Some useful daily utility scripts.
Home-page: https://github.com/JarryShaw/macdaily#macdaily
Author: Jarry Shaw
Author-email: jarryshaw@icloud.com
License: GNU General Public License v3 (GPLv3)
Keywords: daily utility script
Platform: UNKNOWN
Classifier: Development Status :: 5 - Production/Stable
Classifier: Environment :: Console
Classifier: Environment :: MacOS X
Classifier: Intended Audience :: Developers
Classifier: License :: OSI Approved :: GNU General Public License v3 (GPLv3)
Classifier: Natural Language :: English
Classifier: Operating System :: MacOS
Classifier: Operating System :: Unix
Classifier: Programming Language :: Python
Classifier: Programming Language :: Python :: 3
Classifier: Programming Language :: Python :: 3.6
Classifier: Programming Language :: Python :: 3 :: Only
Classifier: Programming Language :: Python :: Implementation
Classifier: Programming Language :: Python :: Implementation :: CPython
Classifier: Programming Language :: Python :: Implementation :: PyPy
Classifier: Programming Language :: Unix Shell
Classifier: Topic :: Utilities
Requires-Python: >=3.6
Provides-Extra: pipdeptree
Requires-Dist: setuptools
Provides-Extra: pipdeptree
Requires-Dist: pipdeptree; extra == 'pipdeptree'
